azext_msgraphusersuser/__init__.py
azext_msgraphusersuser/action.py
azext_msgraphusersuser/azext_metadata.json
azext_msgraphusersuser/custom.py
azext_msgraphusersuser/generated/__init__.py
azext_msgraphusersuser/generated/_client_factory.py
azext_msgraphusersuser/generated/_help.py
azext_msgraphusersuser/generated/_params.py
azext_msgraphusersuser/generated/_validators.py
azext_msgraphusersuser/generated/action.py
azext_msgraphusersuser/generated/commands.py
azext_msgraphusersuser/generated/custom.py
azext_msgraphusersuser/manual/__init__.py
azext_msgraphusersuser/tests/__init__.py
azext_msgraphusersuser/tests/latest/__init__.py
azext_msgraphusersuser/tests/latest/preparers.py
azext_msgraphusersuser/tests/latest/test_msgraphusersuser_scenario.py
azext_msgraphusersuser/vendored_sdks/__init__.py
azext_msgraphusersuser/vendored_sdks/msgraphusersuser/__init__.py
azext_msgraphusersuser/vendored_sdks/msgraphusersuser/_configuration.py
azext_msgraphusersuser/vendored_sdks/msgraphusersuser/_users_user.py
azext_msgraphusersuser/vendored_sdks/msgraphusersuser/aio/__init__.py
azext_msgraphusersuser/vendored_sdks/msgraphusersuser/aio/_configuration_async.py
azext_msgraphusersuser/vendored_sdks/msgraphusersuser/aio/_users_user_async.py
azext_msgraphusersuser/vendored_sdks/msgraphusersuser/aio/operations_async/__init__.py
azext_msgraphusersuser/vendored_sdks/msgraphusersuser/aio/operations_async/_user_operations_async.py
azext_msgraphusersuser/vendored_sdks/msgraphusersuser/aio/operations_async/_user_user_operations_async.py
azext_msgraphusersuser/vendored_sdks/msgraphusersuser/models/__init__.py
azext_msgraphusersuser/vendored_sdks/msgraphusersuser/models/_models.py
azext_msgraphusersuser/vendored_sdks/msgraphusersuser/models/_models_py3.py
azext_msgraphusersuser/vendored_sdks/msgraphusersuser/models/_users_user_enums.py
azext_msgraphusersuser/vendored_sdks/msgraphusersuser/operations/__init__.py
msgraphusersuser-0.1.0.dist-info/METADATA
msgraphusersuser-0.1.0.dist-info/WHEEL
msgraphusersuser-0.1.0.dist-info/top_level.txt
msgraphusersuser-0.1.0.dist-info/RECORD
