Metadata-Version: 2.1
Name: msgraphusersuser
Version: 0.1.0
Summary: Microsoft Azure Command-Line Tools UsersUser Extension
Home-page: https://github.com/Azure/azure-cli-extensions/tree/master/src/msgraphusersuser
Author: Microsoft Corporation
Author-email: azpycli@microsoft.com
License: MIT
